tinynarm/__init__.py
tinynarm/comparison.py
tinynarm/discretization.py
tinynarm/item.py
tinynarm/tinynarm.py
tinynarm/utils.py
tinynarm-0.3.2.dist-info/LICENSE
tinynarm-0.3.2.dist-info/METADATA
tinynarm-0.3.2.dist-info/WHEEL
tinynarm-0.3.2.dist-info/RECORD
