Metadata-Version: 2.1
Name: tinynarm
Version: 0.3.2
Summary: Simplify numerical association rule mining
Home-page: https://github.com/firefly-cpp/tinynarm
Keywords: association rule mining,data science,numerical association rule mining,tinyML
Author: Iztok Fister Jr.
Author-email: iztok@iztok-jr-fister.eu
Requires-Python: >=3.9,<4.0
Classifier: Programming Language :: Python :: 3
Classifier: Programming Language :: Python :: 3.9
Classifier: Programming Language :: Python :: 3.10
Classifier: Programming Language :: Python :: 3.11
Classifier: Programming Language :: Python :: 3.12
Requires-Dist: niaarm (>=0.3.9,<0.4.0)
Project-URL: Repository, https://github.com/firefly-cpp/tinynarm
